MANIFEST.in
README.md
setup.py
get_names_malinowa.egg-info/PKG-INFO
get_names_malinowa.egg-info/SOURCES.txt
get_names_malinowa.egg-info/dependency_links.txt
get_names_malinowa.egg-info/requires.txt
get_names_malinowa.egg-info/top_level.txt
getnamesmalinowa/__init__.py
getnamesmalinowa/getnames.py