Metadata-Version: 1.0
Name: get-names-malinowa
Version: 0.1.0
Summary: Package with functions printing random names, surnames, or both
Home-page: UNKNOWN
Author: malinowa
Author-email: amt-mal@wp.pl
License: UNKNOWN
Platform: UNKNOWN
